<registry xmlns="http://apache.org/wink/common/internal/model/admin">
    <resources>
        <resource>
            <uri>/thirdPartys</uri>
            <class-name>org.energyos.espi.ThirdParty.resources.ThirdPartysResource</class-name>
            <priority>0.5</priority>
            <workspace>Third Party Retail Customers</workspace>
            <collection>ThirdPartys</collection>
            <methods>
                <method>
                    <name>GET</name>
                    <accept-media-types/>
                    <produced-media-types>
                        <produced-media-type>application/atom+xml</produced-media-type>
                        <produced-media-type>application/json</produced-media-type>
                        <produced-media-type>text/html</produced-media-type>
                        <produced-media-type>text/csv</produced-media-type>
                    </produced-media-types>
                    <query-parameters>
                        <parameter>q</parameter>
                        <parameter>severity</parameter>
                        <parameter>assignedTo</parameter>
                    </query-parameters>
                    <matrix-parameters/>
                </method>
                <method>
                    <name>GET</name>
                    <accept-media-types/>
                    <produced-media-types>
                        <produced-media-type>application/opensearchdescription+xml</produced-media-type>
                    </produced-media-types>
                    <query-parameters/>
                    <matrix-parameters/>
                </method>
                <method>
                    <name>POST</name>
                    <accept-media-types>
                        <accept-media-type>text/csv</accept-media-type>
                    </accept-media-types>
                    <produced-media-types>
                        <produced-media-type>application/atom+xml</produced-media-type>
                        <produced-media-type>application/json</produced-media-type>
                        <produced-media-type>application/xml</produced-media-type>
                    </produced-media-types>
                    <query-parameters/>
                    <matrix-parameters/>
                </method>
                <method>
                    <name>POST</name>
                    <accept-media-types>
                        <accept-media-type>application/atom+xml</accept-media-type>
                        <accept-media-type>application/xml</accept-media-type>
                        <accept-media-type>application/json</accept-media-type>
                    </accept-media-types>
                    <produced-media-types>
                        <produced-media-type>application/atom+xml</produced-media-type>
                        <produced-media-type>application/json</produced-media-type>
                        <produced-media-type>application/xml</produced-media-type>
                    </produced-media-types>
                    <query-parameters/>
                    <matrix-parameters/>
                </method>
            </methods>
            <sub-resources>
                <sub-resource>
                    <type>Method</type>
                    <method>GET</method>
                    <uri>/thirdPartys{thirdParty}</uri>
                    <accept-media-types/>
                    <produced-media-types>
                        <produced-media-type>application/atom+xml</produced-media-type>
                        <produced-media-type>application/json</produced-media-type>
                        <produced-media-type>application/xml</produced-media-type>
                        <produced-media-type>text/html</produced-media-type>
                    </produced-media-types>
                    <query-parameters/>
                    <matrix-parameters/>
                </sub-resource>
                <sub-resource>
                    <type>Method</type>
                    <method>GET</method>
                    <uri>/thirdPartys{thirdParty}/attachment</uri>
                    <accept-media-types/>
                    <produced-media-types>
                        <produced-media-type>image/jpeg</produced-media-type>
                    </produced-media-types>
                    <query-parameters/>
                    <matrix-parameters/>
                </sub-resource>
                <sub-resource>
                    <type>Method</type>
                    <method>PUT</method>
                    <uri>/thirdPartys{thirdParty}</uri>
                    <accept-media-types>
                        <accept-media-type>application/atom+xml</accept-media-type>
                        <accept-media-type>application/xml</accept-media-type>
                    </accept-media-types>
                    <produced-media-types>
                        <produced-media-type>application/atom+xml</produced-media-type>
                        <produced-media-type>application/json</produced-media-type>
                        <produced-media-type>application/xml</produced-media-type>
                    </produced-media-types>
                    <query-parameters/>
                    <matrix-parameters/>
                </sub-resource>
                <sub-resource>
                    <type>Method</type>
                    <method>DELETE</method>
                    <uri>/thirdPartys{thirdParty}</uri>
                    <accept-media-types/>
                    <produced-media-types>
                        <produced-media-type>application/atom+xml</produced-media-type>
                        <produced-media-type>application/json</produced-media-type>
                        <produced-media-type>application/xml</produced-media-type>
                    </produced-media-types>
                    <query-parameters/>
                    <matrix-parameters/>
                </sub-resource>
            </sub-resources>
        </resource>
        <resource>
            <uri>/usagepoints</uri>
            <class-name>org.energyos.espi.ThirdParty.resources.UsagePointsResource</class-name>
            <priority>0.5</priority>
            <workspace>Retail Customers</workspace>
            <collection>Usage Points</collection>
            <methods>
                <method>
                    <name>GET</name>
                    <accept-media-types/>
                    <produced-media-types>
                        <produced-media-type>application/atom+xml</produced-media-type>
                        <produced-media-type>application/json</produced-media-type>
                    </produced-media-types>
                    <query-parameters/>
                    <matrix-parameters/>
                </method>
                <method>
                    <name>GET</name>
                    <accept-media-types/>
                    <produced-media-types>
                        <produced-media-type>text/html</produced-media-type>
                    </produced-media-types>
                    <query-parameters/>
                    <matrix-parameters/>
                </method>
            </methods>
            <sub-resources>
                <sub-resource>
                    <type>Method</type>
                    <method>GET</method>
                    <uri>/usagepoints{usagepoint}</uri>
                    <accept-media-types/>
                    <produced-media-types>
                        <produced-media-type>application/atom+xml</produced-media-type>
                        <produced-media-type>application/json</produced-media-type>
                        <produced-media-type>application/xml</produced-media-type>
                    </produced-media-types>
                    <query-parameters/>
                    <matrix-parameters/>
                </sub-resource>
            </sub-resources>
        </resource>
        <resource>
            <uri>/</uri>
            <class-name>org.apache.wink.server.internal.resources.HtmlServiceDocumentResource</class-name>
            <priority>0.1000000000000000055511151231257827021181583404541015625</priority>
            <methods>
                <method>
                    <name>GET</name>
                    <accept-media-types/>
                    <produced-media-types>
                        <produced-media-type>text/html</produced-media-type>
                    </produced-media-types>
                    <query-parameters/>
                    <matrix-parameters/>
                </method>
                <method>
                    <name>GET</name>
                    <accept-media-types/>
                    <produced-media-types>
                        <produced-media-type>application/atomsvc+xml</produced-media-type>
                    </produced-media-types>
                    <query-parameters/>
                    <matrix-parameters/>
                </method>
            </methods>
            <sub-resources/>
        </resource>
    </resources>
